athena/__init__.py
athena/__main__.py
athena/_metadata.py
athena/athena_json.py
athena/cache.py
athena/client.py
athena/defaults.py
athena/display.py
athena/exceptions.py
athena/fake.py
athena/file.py
athena/format.py
athena/history.py
athena/humanize.py
athena/module.py
athena/request.py
athena/resource.py
athena/run.py
athena/server.py
athena/state.py
athena/status.py
athena/test.py
athena/trace.py
athena/watch.py
haondt_athena-5.0.4.dist-info/entry_points.txt
haondt_athena-5.0.4.dist-info/LICENSE
haondt_athena-5.0.4.dist-info/WHEEL
haondt_athena-5.0.4.dist-info/METADATA
haondt_athena-5.0.4.dist-info/RECORD
