Metadata-Version: 2.3
Name: haondt-athena
Version: 5.0.4
Summary: a file-based rest api client
Keywords: api,rest
Author: haondt
Requires-Python: >=3.11
Classifier: License :: OSI Approved :: MIT License
Requires-Dist: click>=8.1.7
Requires-Dist: PyYAML>=6.0.1
Requires-Dist: requests>=2.31.0
Requires-Dist: aiohttp>=3.8.6
Requires-Dist: Pygments>=2.16.1
Requires-Dist: watchdog>=4.0.0
Requires-Dist: Faker>=25.8.0
Requires-Dist: Flask==3.0.2
Project-URL: Homepage, https://gitlab.com/haondt/athena
Project-URL: Repository, https://gitlab.com/haondt/athena
